slimcontext/__init__.py
slimcontext/main.py
slimcontext/managers/__init__.py
slimcontext/managers/python.py
slimcontext/parsers/__init__.py
slimcontext/parsers/baseparser.py
slimcontext/parsers/htmlparse/__init__.py
slimcontext/parsers/htmlparse/htmlparser.py
slimcontext/parsers/notebookparse/__init__.py
slimcontext/parsers/notebookparse/notebookparser.py
slimcontext/parsers/parser.py
slimcontext/parsers/pyparse/__init__.py
slimcontext/parsers/pyparse/assignments.py
slimcontext/parsers/pyparse/classes.py
slimcontext/parsers/pyparse/expressions.py
slimcontext/parsers/pyparse/functions.py
slimcontext/parsers/pyparse/imports.py
slimcontext/parsers/pyparse/pybase.py
slimcontext/parsers/pyparse/pyparse_tools.py
slimcontext/parsers/pyparse/pyparser.py
slimcontext/parsers/utils.py
slimcontext/utils/__init__.py
slimcontext/utils/gitrepo_tools.py
slimcontext/utils/logger.py
slimcontext/utils/token_counter.py
slimcontext-0.9.0.dist-info/LICENSE
slimcontext-0.9.0.dist-info/METADATA
slimcontext-0.9.0.dist-info/WHEEL
slimcontext-0.9.0.dist-info/entry_points.txt
slimcontext-0.9.0.dist-info/RECORD
