Metadata-Version: 2.3
Name: slimcontext
Version: 0.9.0
Summary: A tool to turn a git repository into context for LLMs.
License: MIT
Keywords: LLM,Git,Context,Tool,ChatBot
Author: Neil Schneider
Author-email: schneider.neil@gmail.com
Requires-Python: >=3.10
Classifier: Intended Audience :: Developers
Classifier: License :: OSI Approved :: MIT License
Classifier: Operating System :: OS Independent
Classifier: Programming Language :: Python :: 3
Classifier: Programming Language :: Python :: 3.10
Classifier: Programming Language :: Python :: 3.11
Classifier: Programming Language :: Python :: 3.12
Classifier: Programming Language :: Python :: 3.13
Classifier: Topic :: Software Development :: Libraries
Classifier: Topic :: Software Development :: Version Control
Requires-Dist: beautifulsoup4 (>=4.12.3,<5.0.0)
Requires-Dist: click (>=8.1.7,<9.0.0)
Requires-Dist: nbformat (>=5.10.4,<6.0.0)
Requires-Dist: tiktoken (>=0.8.0,<1.0.0)
Project-URL: Homepage, https://gitlab.com/notorious-community/slimcontext
